MANIFEST.in
README.rst
setup.py
mturkotreeutils.egg-info/PKG-INFO
mturkotreeutils.egg-info/SOURCES.txt
mturkotreeutils.egg-info/dependency_links.txt
mturkotreeutils.egg-info/requires.txt
mturkotreeutils.egg-info/top_level.txt
otree_mturk_utils/__init__.py
otree_mturk_utils/apps.py
otree_mturk_utils/consumers.py
otree_mturk_utils/models.py
otree_mturk_utils/tests.py
otree_mturk_utils/views.py
otree_mturk_utils/_builtin/__init__.py
otree_mturk_utils/migrations/__init__.py
otree_mturk_utils/otree_extensions/__init__.py
otree_mturk_utils/otree_extensions/routing.py
otree_mturk_utils/templates/otree_mturk_utils/BigFive.html
otree_mturk_utils/templates/otree_mturk_utils/BigFive.js
otree_mturk_utils/templates/otree_mturk_utils/CustomWaitPage.html
otree_mturk_utils/templates/otree_mturk_utils/RealEffortTask.html
otree_mturk_utils/templates/otree_mturk_utils/RealEffortTask.js
otree_mturk_utils/templates/otree_mturk_utils/waiting_page_channel.js.html
otree_mturk_utils/templates/radiogrid/radiogrid_input.html
otree_mturk_utils/templates/radiogrid/radiogrid_widget.html