Metadata-Version: 1.1
Name: mturkotreeutils
Version: 0.0.2
Summary: set of utilities for oTree and mTurk
Home-page: https://github.com/chapkovski/custom-waiting-page-for-mturk
Author: Essi Kujansuu - Nicolas Gruyer/Economics Games - Philipp Chapkovski
Author-email: chapkovski@gmail.com
License: MIT License
Platform: UNKNOWN
Classifier: Environment :: Web Environment
Classifier: Framework :: Django
Classifier: Intended Audience :: Developers
Classifier: License :: OSI Approved :: MIT License
Classifier: Operating System :: OS Independent
Classifier: Programming Language :: Python
Classifier: Programming Language :: Python :: 3
Classifier: Programming Language :: Python :: 3.4
Classifier: Programming Language :: Python :: 3.5
Classifier: Topic :: Internet :: WWW/HTTP
Classifier: Topic :: Internet :: WWW/HTTP :: Dynamic Content
